pydtree/__init__.py
pydtree/tree.py
pydtree/themes/__init__.py
pydtree/themes/ascii.py
pydtree/themes/unicode.py
pydtree/types/__init__.py
pydtree/types/render_data.py
pydtree/types/theme.py
pydtree/types/treenode.py
pydtree-1.1.dist-info/licenses/LICENSE
pydtree-1.1.dist-info/METADATA
pydtree-1.1.dist-info/WHEEL
pydtree-1.1.dist-info/top_level.txt
pydtree-1.1.dist-info/RECORD
